README.md
setup.py
acrawler_prometheus/__init__.py
acrawler_prometheus/handler.py
acrawler_prometheus.egg-info/PKG-INFO
acrawler_prometheus.egg-info/SOURCES.txt
acrawler_prometheus.egg-info/dependency_links.txt
acrawler_prometheus.egg-info/requires.txt
acrawler_prometheus.egg-info/top_level.txt