Metadata-Version: 2.1
Name: acrawler-prometheus
Version: 0.0.4
Summary: The handler working with aCrawler and Prometheus
Home-page: https://github.com/wooddance/acrawler-prometheus
Author: wooddance
Author-email: zireael.me@gmail.com
License: UNKNOWN
Platform: UNKNOWN
Requires-Python: >=3.6.0
